pyagree/__init__.py
pyagree/common.py
pyagree/inf_agreement.py
pyagree/inf_theory.py
pyagree/standard.py
pyagree/test.py
pyagree-0.0.4.dist-info/LICENSE
pyagree-0.0.4.dist-info/METADATA
pyagree-0.0.4.dist-info/WHEEL
pyagree-0.0.4.dist-info/top_level.txt
pyagree-0.0.4.dist-info/RECORD
