Metadata-Version: 2.1
Name: pyagree
Version: 0.0.4
Summary: A simple Python package to compute some inter-rater agreement measures.
Home-page: https://github.com/albertocasagrande/pyagree
Author: Alberto Casagrande
Author-email: acasagrande@units.it
License: MIT License
Project-URL: Documentation, https://readthedocs.org/projects/pyagree/
Project-URL: Source Code, https://github.com/albertocasagrande/pyagree
Keywords: inter-rater agreement measures
Platform: UNKNOWN
Classifier: Development Status :: 4 - Beta
Classifier: Environment :: Console
Classifier: Intended Audience :: Developers
Classifier: Intended Audience :: Information Technology
Classifier: Topic :: Scientific/Engineering
Classifier: Programming Language :: Python
Classifier: Programming Language :: Python :: 3.6
Classifier: Operating System :: OS Independent
Classifier: License :: OSI Approved :: MIT License
Requires-Python: >=3.6
Requires-Dist: numpy
Provides-Extra: doc
Requires-Dist: sphinxcontrib.bibtex ; extra == 'doc'
Requires-Dist: sphinxcontrib.katex ; extra == 'doc'
Requires-Dist: numpy ; extra == 'doc'
